neutron/__init__.py
neutron/client.py
neutron/interactive_model.py
neutron/server.py
neutron/utilities.py
neutron_ai-1.0.0b7.dist-info/LICENSE.md
neutron_ai-1.0.0b7.dist-info/METADATA
neutron_ai-1.0.0b7.dist-info/WHEEL
neutron_ai-1.0.0b7.dist-info/entry_points.txt
neutron_ai-1.0.0b7.dist-info/top_level.txt
neutron_ai-1.0.0b7.dist-info/RECORD
