Metadata-Version: 2.1
Name: neutron-ai
Version: 1.0.0b7
Summary: AI Powered Ethical Hacking Assistant
Home-page: https://github.com/berylliumsec/neutron
Author: David I
Author-email: david@berylliumsec.com
License: BSD
Keywords: AI,Ethical Hacking
Classifier: Development Status :: 4 - Beta
Classifier: Intended Audience :: Developers
Classifier: License :: OSI Approved :: BSD License
Classifier: Operating System :: OS Independent
Classifier: Programming Language :: Python :: 3
Classifier: Programming Language :: Python :: 3.10
Classifier: Topic :: Software Development :: Libraries :: Python Modules
Classifier: Topic :: Security
Classifier: Topic :: Text Processing :: Linguistic
Requires-Python: >=3.10
License-File: LICENSE.md
Requires-Dist: torch >=1.0.1
Requires-Dist: transformers >=4.34.0
Requires-Dist: fastapi
Requires-Dist: uvicorn
Requires-Dist: pydantic
Requires-Dist: langchain
Requires-Dist: regex
Requires-Dist: argparse
Requires-Dist: typing-extensions
